{
  "parent": "minecraft:block/block",
  "loader": "gtceu:machine",
  "machine": "gtfrivolous:lv_magic_hull",
  "replaceable_textures": [
    "bottom",
    "top",
    "side"
  ],
  "variants": {
    "is_formed=false": {
      "model": {
        "parent": "gtceu:block/machine/part/hull",
        "textures": {
          "bottom": "gtfrivolous:block/casings/voltage/lv/bottom",
          "side": "gtfrivolous:block/casings/voltage/lv/side",
          "top": "gtfrivolous:block/casings/voltage/lv/top"
        }
      }
    },
    "is_formed=true": {
      "model": {
        "parent": "gtceu:block/machine/part/hull",
        "textures": {
          "bottom": "gtfrivolous:block/casings/voltage/lv/bottom",
          "side": "gtfrivolous:block/casings/voltage/lv/side",
          "top": "gtfrivolous:block/casings/voltage/lv/top"
        }
      }
    }
  }
}